pycompadre-1.4.5.dist-info/LICENSE.md
pycompadre-1.4.5.dist-info/top_level.txt
pycompadre-1.4.5.dist-info/RECORD
pycompadre-1.4.5.dist-info/WHEEL
pycompadre-1.4.5.dist-info/METADATA
pycompadre.libs/libgomp-f7e03b3e.so.1.0.0
pycompadre/libcompadre.so
pycompadre/__init__.py
pycompadre/libkokkoskernels.so
pycompadre/libkokkoscore.so.3.0.0
pycompadre/libkokkoscontainers.so
pycompadre/libkokkoscore.so
pycompadre/libkokkoscontainers.so.3.0.0
pycompadre/_pycompadre.cpython-39-x86_64-linux-gnu.so
pycompadre/examples/pycompadre_example_1d.py
pycompadre/examples/test_pycompadre.py
pycompadre/examples/test_pycompadre_manifold.py
pycompadre/examples/pycompadre_kernels.py
pycompadre/examples/pycompadre_example_2d.py
